dev_env_testing/__init__.py
dev_env_testing/foo.py
dev_env_testing-1.22.0.data/scripts/no-op.sh
dev_env_testing-1.22.0.dist-info/DESCRIPTION.rst
dev_env_testing-1.22.0.dist-info/METADATA
dev_env_testing-1.22.0.dist-info/RECORD
dev_env_testing-1.22.0.dist-info/WHEEL
dev_env_testing-1.22.0.dist-info/metadata.json
dev_env_testing-1.22.0.dist-info/top_level.txt
