Metadata-Version: 2.0
Name: dev-env-testing
Version: 1.22.0
Summary: Dev Env Testing
Home-page: https://github.com/simonsdave/dev-env-testing
Author: Dave Simons
Author-email: simonsdave@gmail.com
Maintainer: Dave Simons
Maintainer-email: simonsdave@gmail.com
License: MIT
Download-URL: https://github.com/simonsdave/dev-env-testing/tarball/v1.22.0
Keywords: development,tools,testing
Platform: UNKNOWN
Classifier: Development Status :: 5 - Production/Stable
Classifier: Intended Audience :: Developers
Classifier: Natural Language :: English
Classifier: License :: OSI Approved :: MIT License
Classifier: Operating System :: OS Independent
Classifier: Programming Language :: Python
Classifier: Programming Language :: Python :: 3.7
Classifier: Programming Language :: Python :: Implementation :: CPython
Classifier: Topic :: Software Development :: Libraries :: Python Modules
